mynomar/__init__.py
mynomar/modificar/__init__.py
mynomar/modificar/texto.py
mynomar/normalizar/__init__.py
mynomar/normalizar/nome.py
mynomar-0.0.1.dist-info/METADATA
mynomar-0.0.1.dist-info/WHEEL
mynomar-0.0.1.dist-info/top_level.txt
mynomar-0.0.1.dist-info/RECORD
