Metadata-Version: 2.1
Name: mynomar
Version: 0.0.1
Summary: Normaliza nomes de arquivos.
Home-page: https://github.com/alab434/des-pac-dio
Author: Almyr P.
Author-email: my_email@example.com
Requires-Python: >=3.10
